README
setup.py
sshtoy/__init__.py
sshtoy/main.py
sshtoy/ssh.py
sshtoy.egg-info/PKG-INFO
sshtoy.egg-info/SOURCES.txt
sshtoy.egg-info/dependency_links.txt
sshtoy.egg-info/entry_points.txt
sshtoy.egg-info/requires.txt
sshtoy.egg-info/top_level.txt