Metadata-Version: 1.0
Name: sshtoy
Version: 1.0.5
Summary: Connecting to remote host with one command.
Home-page: https://github.com/xiongharry/sshtoy
Author: Xiong Harry
Author-email: xiongharry@gmail.com
License: UNKNOWN
Platform: UNKNOWN
Classifier: Environment :: Console
Classifier: Intended Audience :: Developers
Classifier: Intended Audience :: System Administrators
Classifier: License :: OSI Approved :: BSD License
Classifier: Operating System :: MacOS :: MacOS X
Classifier: Operating System :: Unix
Classifier: Operating System :: POSIX
Classifier: Programming Language :: Python
Classifier: Programming Language :: Python :: 2.5
Classifier: Programming Language :: Python :: 2.6
Classifier: Programming Language :: Python :: 2.7
Classifier: Topic :: System :: Software Distribution
Classifier: Topic :: System :: Systems Administration
